socket_plus/__init__.py
socket_plus/main.py
socket_plus-0.0.2.dist-info/LICENSE
socket_plus-0.0.2.dist-info/METADATA
socket_plus-0.0.2.dist-info/WHEEL
socket_plus-0.0.2.dist-info/top_level.txt
socket_plus-0.0.2.dist-info/RECORD
