Metadata-Version: 2.1
Name: socket-plus
Version: 0.0.2
Summary: A librairie in python to comunicate more efficiently possible with structures.
Home-page: https://github.com/coco875/socket-plus
Author: coco875
Author-email: pereira.jannin@gmail.com
License: UNKNOWN
Project-URL: Bug Tracker, https://github.com/coco875/socket-plus/issues
Platform: UNKNOWN
Classifier: Programming Language :: Python :: 3
Classifier: License :: OSI Approved :: MIT License
Classifier: Operating System :: OS Independent
Requires-Python: >=3.9
License-File: LICENSE
